{"version":"3.8.0","examples":[{"id":"./spec/person_spec.rb[1:1:1:1]","description":"a new person is instantiated with a name","full_description":"Person instantiation ::new a new person is instantiated with a name","status":"passed","file_path":"./spec/person_spec.rb","line_number":10,"run_time":0.002425963,"pending_message":null},{"id":"./spec/person_spec.rb[1:1:2:1:1]","description":"a new person knows its name once he/she has been initialized","full_description":"Person instantiation #initialize #name a new person knows its name once he/she has been initialized","status":"passed","file_path":"./spec/person_spec.rb","line_number":17,"run_time":0.002476163,"pending_message":null},{"id":"./spec/person_spec.rb[1:1:2:1:2]","description":"a new person instance cannot overwrite the name it was instantied with","full_description":"Person instantiation #initialize #name a new person instance cannot overwrite the name it was instantied with","status":"passed","file_path":"./spec/person_spec.rb","line_number":23,"run_time":0.004355601,"pending_message":null},{"id":"./spec/person_spec.rb[1:1:2:2:1]","description":"a new person instance is initialized with a bank_account balance of $25","full_description":"Person instantiation #initialize #bank_account a new person instance is initialized with a bank_account balance of $25","status":"passed","file_path":"./spec/person_spec.rb","line_number":31,"run_time":0.000186924,"pending_message":null},{"id":"./spec/person_spec.rb[1:1:2:2:2]","description":"a person instance can change his/her bank_account amount","full_description":"Person instantiation #initialize #bank_account a person instance can change his/her bank_account amount","status":"passed","file_path":"./spec/person_spec.rb","line_number":35,"run_time":0.000135927,"pending_message":null},{"id":"./spec/person_spec.rb[1:1:2:3:1]","description":" a new person instance is initialized with a happiness index of 8","full_description":"Person instantiation #initialize #happiness  a new person instance is initialized with a happiness index of 8","status":"passed","file_path":"./spec/person_spec.rb","line_number":44,"run_time":0.000128663,"pending_message":null},{"id":"./spec/person_spec.rb[1:1:2:3:2]","description":"a person instance can change his/her happiness index","full_description":"Person instantiation #initialize #happiness a person instance can change his/her happiness index","status":"passed","file_path":"./spec/person_spec.rb","line_number":48,"run_time":0.000137846,"pending_message":null},{"id":"./spec/person_spec.rb[1:1:2:3:3]","description":"a person's happiness doesn't exceed 10","full_description":"Person instantiation #initialize #happiness a person's happiness doesn't exceed 10","status":"passed","file_path":"./spec/person_spec.rb","line_number":56,"run_time":0.000129636,"pending_message":null},{"id":"./spec/person_spec.rb[1:1:2:3:4]","description":"a person's happiness doesn't go below 0","full_description":"Person instantiation #initialize #happiness a person's happiness doesn't go below 0","status":"passed","file_path":"./spec/person_spec.rb","line_number":64,"run_time":0.000117368,"pending_message":null},{"id":"./spec/person_spec.rb[1:1:2:4:1]","description":"a person instance is initialized with a hygiene index of 8","full_description":"Person instantiation #initialize #hygiene a person instance is initialized with a hygiene index of 8","status":"passed","file_path":"./spec/person_spec.rb","line_number":74,"run_time":0.000182487,"pending_message":null},{"id":"./spec/person_spec.rb[1:1:2:4:2]","description":"a person instance can change its hygiene index","full_description":"Person instantiation #initialize #hygiene a person instance can change its hygiene index","status":"passed","file_path":"./spec/person_spec.rb","line_number":78,"run_time":0.000190742,"pending_message":null},{"id":"./spec/person_spec.rb[1:1:2:4:3]","description":"a person instance's hygiene index cannot exceed 10 ","full_description":"Person instantiation #initialize #hygiene a person instance's hygiene index cannot exceed 10 ","status":"passed","file_path":"./spec/person_spec.rb","line_number":86,"run_time":0.000176965,"pending_message":null},{"id":"./spec/person_spec.rb[1:1:2:4:4]","description":" a person instance hygiene index cannot be less than 0 ","full_description":"Person instantiation #initialize #hygiene  a person instance hygiene index cannot be less than 0 ","status":"passed","file_path":"./spec/person_spec.rb","line_number":94,"run_time":0.000128679,"pending_message":null},{"id":"./spec/person_spec.rb[1:2:1:1]","description":"returns true if happiness is greater than seven, else false","full_description":"Person non-attribute instance methods #happy? returns true if happiness is greater than seven, else false","status":"passed","file_path":"./spec/person_spec.rb","line_number":112,"run_time":0.000137168,"pending_message":null},{"id":"./spec/person_spec.rb[1:2:2:1]","description":"returns true if hygiene is greater than seven, else false","full_description":"Person non-attribute instance methods #clean? returns true if hygiene is greater than seven, else false","status":"passed","file_path":"./spec/person_spec.rb","line_number":121,"run_time":0.000176645,"pending_message":null},{"id":"./spec/person_spec.rb[1:2:3:1]","description":"accepts an argument of salary","full_description":"Person non-attribute instance methods #get_paid accepts an argument of salary","status":"passed","file_path":"./spec/person_spec.rb","line_number":130,"run_time":0.000204038,"pending_message":null},{"id":"./spec/person_spec.rb[1:2:3:2]","description":"increments bank_account by the salary","full_description":"Person non-attribute instance methods #get_paid increments bank_account by the salary","status":"passed","file_path":"./spec/person_spec.rb","line_number":134,"run_time":0.000116641,"pending_message":null},{"id":"./spec/person_spec.rb[1:2:3:3]","description":"returns 'all about the benjamins'","full_description":"Person non-attribute instance methods #get_paid returns 'all about the benjamins'","status":"passed","file_path":"./spec/person_spec.rb","line_number":140,"run_time":0.000116129,"pending_message":null},{"id":"./spec/person_spec.rb[1:2:4:1]","description":"makes the person cleaner by 4 points","full_description":"Person non-attribute instance methods #take_bath makes the person cleaner by 4 points","status":"passed","file_path":"./spec/person_spec.rb","line_number":146,"run_time":0.000182519,"pending_message":null},{"id":"./spec/person_spec.rb[1:2:4:2]","description":"returns a song","full_description":"Person non-attribute instance methods #take_bath returns a song","status":"passed","file_path":"./spec/person_spec.rb","line_number":152,"run_time":0.000150671,"pending_message":null},{"id":"./spec/person_spec.rb[1:2:4:3]","description":"can't make a person cleaner by 10 points (hint: use the custom #hygiene= method)","full_description":"Person non-attribute instance methods #take_bath can't make a person cleaner by 10 points (hint: use the custom #hygiene= method)","status":"passed","file_path":"./spec/person_spec.rb","line_number":157,"run_time":0.000145912,"pending_message":null},{"id":"./spec/person_spec.rb[1:2:4:4]","description":"calls on the #hygiene= method to increment hygiene","full_description":"Person non-attribute instance methods #take_bath calls on the #hygiene= method to increment hygiene","status":"passed","file_path":"./spec/person_spec.rb","line_number":163,"run_time":0.012189123,"pending_message":null},{"id":"./spec/person_spec.rb[1:2:5:1]","description":"makes the person dirtier by 3 points","full_description":"Person non-attribute instance methods #work_out makes the person dirtier by 3 points","status":"failed","file_path":"./spec/person_spec.rb","line_number":172,"run_time":0.000217773,"pending_message":null,"exception":{"class":"NoMethodError","message":"undefined method `work_out' for #<Person:0x00000002bb2ce8>","backtrace":["/home/compiled-modal-2586/oo-person-houston-web-111918/spec/person_spec.rb:174:in `block (4 levels) in <top (required)>'","/usr/local/rvm/gems/ruby-2.3.1/gems/rspec-core-3.8.0/lib/rspec/core/example.rb:254:in `instance_exec'","/usr/local/rvm/gems/ruby-2.3.1/gems/rspec-core-3.8.0/lib/rspec/core/example.rb:254:in `block in run'","/usr/local/rvm/gems/ruby-2.3.1/gems/rspec-core-3.8.0/lib/rspec/core/example.rb:500:in `block in with_around_and_singleton_context_hooks'","/usr/local/rvm/gems/ruby-2.3.1/gems/rspec-core-3.8.0/lib/rspec/core/example.rb:457:in `block in with_around_example_hooks'","/usr/local/rvm/gems/ruby-2.3.1/gems/rspec-core-3.8.0/lib/rspec/core/hooks.rb:464:in `block in run'","/usr/local/rvm/gems/ruby-2.3.1/gems/rspec-core-3.8.0/lib/rspec/core/hooks.rb:602:in `run_around_example_hooks_for'","/usr/local/rvm/gems/ruby-2.3.1/gems/rspec-core-3.8.0/lib/rspec/core/hooks.rb:464:in `run'","/usr/local/rvm/gems/ruby-2.3.1/gems/rspec-core-3.8.0/lib/rspec/core/example.rb:457:in `with_around_example_hooks'","/usr/local/rvm/gems/ruby-2.3.1/gems/rspec-core-3.8.0/lib/rspec/core/example.rb:500:in `with_around_and_singleton_context_hooks'","/usr/local/rvm/gems/ruby-2.3.1/gems/rspec-core-3.8.0/lib/rspec/core/example.rb:251:in `run'","/usr/local/rvm/gems/ruby-2.3.1/gems/rspec-core-3.8.0/lib/rspec/core/example_group.rb:629:in `block in run_examples'","/usr/local/rvm/gems/ruby-2.3.1/gems/rspec-core-3.8.0/lib/rspec/core/example_group.rb:625:in `map'","/usr/local/rvm/gems/ruby-2.3.1/gems/rspec-core-3.8.0/lib/rspec/core/example_group.rb:625:in `run_examples'","/usr/local/rvm/gems/ruby-2.3.1/gems/rspec-core-3.8.0/lib/rspec/core/example_group.rb:591:in `run'","/usr/local/rvm/gems/ruby-2.3.1/gems/rspec-core-3.8.0/lib/rspec/core/example_group.rb:592:in `block in run'","/usr/local/rvm/gems/ruby-2.3.1/gems/rspec-core-3.8.0/lib/rspec/core/example_group.rb:592:in `map'","/usr/local/rvm/gems/ruby-2.3.1/gems/rspec-core-3.8.0/lib/rspec/core/example_group.rb:592:in `run'","/usr/local/rvm/gems/ruby-2.3.1/gems/rspec-core-3.8.0/lib/rspec/core/example_group.rb:592:in `block in run'","/usr/local/rvm/gems/ruby-2.3.1/gems/rspec-core-3.8.0/lib/rspec/core/example_group.rb:592:in `map'","/usr/local/rvm/gems/ruby-2.3.1/gems/rspec-core-3.8.0/lib/rspec/core/example_group.rb:592:in `run'","/usr/local/rvm/gems/ruby-2.3.1/gems/rspec-core-3.8.0/lib/rspec/core/runner.rb:116:in `block (3 levels) in run_specs'","/usr/local/rvm/gems/ruby-2.3.1/gems/rspec-core-3.8.0/lib/rspec/core/runner.rb:116:in `map'","/usr/local/rvm/gems/ruby-2.3.1/gems/rspec-core-3.8.0/lib/rspec/core/runner.rb:116:in `block (2 levels) in run_specs'","/usr/local/rvm/gems/ruby-2.3.1/gems/rspec-core-3.8.0/lib/rspec/core/configuration.rb:1989:in `with_suite_hooks'","/usr/local/rvm/gems/ruby-2.3.1/gems/rspec-core-3.8.0/lib/rspec/core/runner.rb:111:in `block in run_specs'","/usr/local/rvm/gems/ruby-2.3.1/gems/rspec-core-3.8.0/lib/rspec/core/reporter.rb:74:in `report'","/usr/local/rvm/gems/ruby-2.3.1/gems/rspec-core-3.8.0/lib/rspec/core/runner.rb:110:in `run_specs'","/usr/local/rvm/gems/ruby-2.3.1/gems/rspec-core-3.8.0/lib/rspec/core/runner.rb:87:in `run'","/usr/local/rvm/gems/ruby-2.3.1/gems/rspec-core-3.8.0/lib/rspec/core/runner.rb:71:in `run'","/usr/local/rvm/gems/ruby-2.3.1/gems/rspec-core-3.8.0/lib/rspec/core/runner.rb:45:in `invoke'","/usr/local/rvm/gems/ruby-2.3.1/gems/rspec-core-3.8.0/exe/rspec:4:in `<top (required)>'","/usr/local/rvm/gems/ruby-2.3.1/bin/rspec:23:in `load'","/usr/local/rvm/gems/ruby-2.3.1/bin/rspec:23:in `<main>'"]}}],"summary":{"duration":0.035179213,"example_count":23,"failure_count":1,"pending_count":0,"errors_outside_of_examples_count":0},"summary_line":"23 examples, 1 failure"}